LICENSE.txt
MANIFEST.in
README.rst
setup.py
tribe_client/__init__.py
tribe_client/app_settings.py
tribe_client/tests.py
tribe_client/urls.py
tribe_client/utils.py
tribe_client/views.py
tribe_client.egg-info/PKG-INFO
tribe_client.egg-info/SOURCES.txt
tribe_client.egg-info/dependency_links.txt
tribe_client.egg-info/requires.txt
tribe_client.egg-info/top_level.txt
tribe_client/management/__init__.py
tribe_client/management/commands/__init__.py
tribe_client/management/commands/tribe_client_pickle_public_genesets.py
tribe_client/templates/display_genesets.html
tribe_client/templates/display_versions.html
tribe_client/templates/establish_connection.html