Metadata-Version: 1.1
Name: tribe-client
Version: 1.1.7
Summary: Portable Python package to connect with the Tribe web service at the University of Pennsylvania
Home-page: https://bitbucket.org/greenelab/tribe-client
Author: Greene Lab
Author-email: team@greenelab.com
License: LICENSE.txt
Platform: UNKNOWN
Classifier: Environment :: Web Environment
Classifier: Framework :: Django
Classifier: Intended Audience :: Developers
Classifier: License :: OSI Approved :: BSD License
Classifier: Operating System :: OS Independent
Classifier: Programming Language :: Python
Classifier: Programming Language :: Python :: 2.7
Classifier: Topic :: Scientific/Engineering :: Bio-Informatics
